Metadata-Version: 2.1
Name: tjru-language-classifier
Version: 0.5
Summary: A simple tajik-russian language classifier
Author: Sobir Bobiev
